{
    "version": 1,
    "license": "CC-BY-NC-SA-3.0",
    "copyright": "Stripes made by BlitzTheSquishy, Countershading made by Emily9031",
    "size":{
        "x": 32,
        "y": 32
    },
        "states": [
        {
            "name": "feroxi-torso-stripes-blitz",
            "directions": 4
        },
        {
            "name": "feroxi-arm-stripes-blitz",
            "directions": 4
        },
        {
            "name": "feroxi-leg-stripes-blitz",
            "directions": 4
        },
        {
            "name": "feroxi-torso-countershading-m",
            "directions": 4
        },
        {
            "name": "feroxi-torso-countershading-f",
            "directions": 4
        },
        {
            "name": "feroxi-torso-stripes-tiger",
            "directions": 4
        },
        {
            "name": "feroxi-arm-stripes-tiger",
            "directions": 4
        },
        {
            "name": "feroxi-leg-stripes-tiger",
            "directions": 4
        },
        {
            "name": "feroxi-head-stripes-tiger",
            "directions": 4
        }
    ]
}
