{
  "version": 1,
  "license": "CC-BY-SA-3.0",
  "copyright": "Taken from tgstation at commit https://github.com/tgstation/tgstation/commit/2e24b7af2221928e4b844a29408e821b60a5fe29, resprite by pyfya (discord) for Space Station 14 server Мёртвый Космос",
  "size": {
    "x": 32,
    "y": 32
  },
  "states": [
    {
      "name": "icon"
    },
    {
      "name": "equipped-BACKPACK",
      "directions": 4
    },
    {
      "name": "inhand-left",
      "directions": 4
    },
    {
      "name": "inhand-right",
      "directions": 4
    }
  ]
}
