{
  "version": 1,
  "license": "CC-BY-SA-3.0",
  "copyright": "Taken from tgstation at commit https://github.com/tgstation/tgstation/commit/c838ba21dae97db345e0113f99596decd1d66039, modified icon/equipped-BELT & all icon/equipped-BELT variations by Prole0 (GitHub)",
  "size": {
    "x": 32,
    "y": 32
  },
  "states": [
    {
      "name": "icon"
    },
    {
      "name": "icon_knife"
    },
    {
      "name": "icon_magazine_pistol"
    },
    {
      "name": "icon_sidearm"
    },
    {
      "name": "icon_speedloader_revolver"
    },
    {
      "name": "icon_powercell"
    },
    {
      "name": "icon_grenade"
    },
    {
      "name": "icon_pack"
    },
    {
      "name": "icon_radio"
    },
    {
      "name": "icon_stunbaton"
    },
    {
      "name": "icon_truncheon"
    },
    {
      "name": "equipped-BELT",
      "directions": 4
    },
    {
      "name": "inhand-left",
      "directions": 4
    },
    {
      "name": "inhand-right",
      "directions": 4
    }
  ]
}
