{
    "version": 1,
    "license": "CC-BY-SA-3.0",
    "copyright": "Assets derived from Wizden SS14 at https://github.com/space-wizards/space-station-14/commit/e4a516514f37d26708e676122eb7c6a95f37b5e3, modified by K-Dynamic (github).",
    "size": {
        "x": 32,
        "y": 32
    },
    "states": [
        {
            "name": "icon"
        },
        {
            "name": "equipped-OUTERCLOTHING",
            "directions": 4
        },
        {
            "name": "equipped-OUTERCLOTHING-vox",
            "directions": 4
        },
        {
            "name": "inhand-left",
            "directions": 4
        },
        {
            "name": "inhand-right",
            "directions": 4
        }
    ]
}
