{
    "version": 1,
    "size": {
        "x": 32,
        "y": 32
    },
    "license": "CC-BY-SA-3.0",
    "copyright": "Taken from /tg/station at commit https://github.com/tgstation/tgstation/commit/b4424d7e79cadb258a65aec2e1bc16cf3d4021dc, https://github.com/tgstation/tgstation/blob/master/icons/obj/weapons/guns/ammo.dmi", 
    "states": [
        {
            "name": "base"
        },
        {
            "name": "icon"
        },
        {
            "name": "base-1"
        },
        {
            "name": "base-2"
        },
        {
            "name": "base-3"
        },
        {
            "name": "base-4"
        },
        {
            "name": "base-5"
        },
        {
            "name": "base-6"
        },
        {
            "name": "high-velocity-1"
        },
        {
            "name": "high-velocity-2"
        },
        {
            "name": "high-velocity-3"
        },
        {
            "name": "high-velocity-4"
        },
        {
            "name": "high-velocity-5"
        },
        {
            "name": "high-velocity-6"
        },
        {
            "name": "practice-1"
        },
        {
            "name": "practice-2"
        },
        {
            "name": "practice-3"
        },
        {
            "name": "practice-4"
        },
        {
            "name": "practice-5"
        },
        {
            "name": "practice-6"
        },
        {
            "name": "rubber-1"
        },
        {
            "name": "rubber-2"
        },
        {
            "name": "rubber-3"
        },
        {
            "name": "rubber-4"
        },
        {
            "name": "rubber-5"
        },
        {
            "name": "rubber-6"
        },
        {
            "name": "base-357"
        },
        {
            "name": "icon-357"
        },
        {
            "name": "threefiftyseven-1"
        },
        {
            "name": "threefiftyseven-2"
        },
        {
            "name": "threefiftyseven-3"
        },
        {
            "name": "threefiftyseven-4"
        },
        {
            "name": "threefiftyseven-5"
        },
        {
            "name": "threefiftyseven-6"
        },
        {
            "name": "threefiftyseven-7"
        }
    ]
}
