{
  "version": 1,
  "size": {"x": 32, "y": 32},
  "license": "CC-BY-SA-3.0",
  "copyright": "Taken from https://github.com/Citadel-Station-13/Citadel-Station-13/commit/84223c65f5caf667a84f3c0f49bc2a41cdc6c4e3. Suitstorage state made by anomalyil (discord) for Space Station 14 server Мёртвый Космос",
  "states": [
    {
      "name": "icon"
    },
    {
      "name": "icon-inhand-left",
      "directions": 4
    },
    {
        "name": "equipped-SUITSTORAGE",
        "directions": 4
    },
    {
      "name": "icon-inhand-right",
      "directions": 4
    }
  ]
}
