{
    "version": 1,
    "size": {
        "x": 32,
        "y": 32
    },
    "license": "CC-BY-SA-3.0",
    "copyright": "Taken from https://github.com/discordia-space/CEV-Eris/",
    "states": [
        {
            "name": "l_st",

        },
        {
            "name": "l_st_0",
            "delays": [
                [
                    0.2,
                    0.2
                ]
            ]
        },
        {
            "name": "l_st_100",

        },
        {
            "name": "l_st_25",

        },
        {
            "name": "l_st_50",

        },
        {
            "name": "l_st_75",

        }
    ]
}