<Document>
  # Воры

  <Box>
    [color=#999999][italic]"Йоинк! Это забираю! И это! Ох, а почему бы и нет?"[/italic][/color]
  </Box>
  <Box>
    <GuideEntityEmbed Entity="ClothingNeckCloakVoid" Caption=""/>
  </Box>

  Воры — хитрые, но мелкие [color=green]преступники[/color], которые не могут удержаться от чужого имущества. После последнего ареста вам имплантировали [bold]пассивизм[/bold], но это не остановит вас от пополнения коллекции.

  ## Искусство кражи
  В отличие от других антагонистов, [bold]вам почти обязательно нужно избегать кровопролития[/bold] из-за импланта.
  Вы можете бежать, только если [color=#cb0000]Служба безопасности[/color] нападёт первой, а поскольку вы действуете в одиночку, помощи ждать неоткуда.

  Но вопреки всему, вы добьётесь своего с помощью настойчивости, ловкости рук, пары инструментов и [color=cyan]карманных навыков[/color].

  Эти навыки дают вам преимущество: [bold]вы можете вытащить вещи у людей, пока они этого не заметили.[/bold] Немного практики — и вы вытащите кошелёк, продолжая беседу.

  Желательно надеть перчатки, потому что отпечатки по-прежнему могут привести к вам, если украденное найдут.


  ## Инструменты профессии
  У вас ещё два козыря: [color=cyan]маяк[/color] и [color=cyan]сумка[/color].

  [color=cyan]Маяк[/color] позволяет отправить добычу домой, если её трудно тащить в эвакуацию. Найдите укромное место, разверните маяк и установите координаты тайника.
  Все вещи рядом будут [bold]телепортированы в ваш сейф[/bold] по завершении смены, выполняя цели.

  Однако, если маяк найдут, вас мгновенно выдадут, и людям будет легко вернуть «потерянные» вещи. [bold]Хорошенько спрячьте его![/bold]

  <Box>
    <GuideEntityEmbed Entity="ThiefBeacon"/>
  </Box>

  Ваша [color=cyan]сумка[/color] содержит всё, что вы захватили. [bold]Можно выбрать два готовых набора,[/bold] чтобы облегчить крупные дела.

  <Box>
    <GuideEntityEmbed Entity="SatchelThief"/>
  </Box>
  <Box>
    <GuideEntityEmbed Entity="Implanter" Caption="Анатомия"/>
    <GuideEntityEmbed Entity="C4" Caption="Взломщик"/>
    <GuideEntityEmbed Entity="ChameleonProjector" Caption="Хамелеон"/>
    <GuideEntityEmbed Entity="BaseUplinkRadio" Caption="Коммуникатор"/>
  </Box>
  <Box>
    <GuideEntityEmbed Entity="NitrousOxideTank" Caption="Сонный газ"/>
    <GuideEntityEmbed Entity="Fulton" Caption="Контрабанда"/>
    <GuideEntityEmbed Entity="Telecrystal" Caption="Синдикат"/>
  </Box>

  ## Основной объект коллекции
  Ваш ворох сделает карьеру. Один день вы хотите поиметь фигурки, другой — промышленное оборудование.

  Не беда, всё окажется в вашей коллекции со временем.

  Вы можете украсть вещи, [bold]доставив их на себя[/bold] в CentComm. Если не получится — [bold]оставьте их у маяка[/bold].

  Некоторые живые цели могут не поддаться. Убедитесь, что они живы и с вами или у маяка, когда смена закончится.

  Возможные желания включают, но не ограничиваются:

  <Box>
    <GuideEntityEmbed Entity="ToyFigurineGreytider" Caption="Фигурки"/>
    <GuideEntityEmbed Entity="PassengerIDCard" Caption="ID карты"/>
    <GuideEntityEmbed Entity="ChemDispenser" Caption="Структуры"/>
    <GuideEntityEmbed Entity="MobCorgiIan" Caption="Животные/Питомцы"/>
  </Box>

</Document>
