{
    "version": 1,
    "license": "CC-BY-SA-4.0",
    "copyright": "Sprites provided by a repository contributor for Space Station 14 Soyuz",
    "size": {
        "x": 32,
        "y": 32
    },
    "states": [
        {
            "name": "icon"
        },
        {
            "name": "active",
            "delays": [
                [
                    0.1,
                    0.1,
                    0.1,
                    0.1
                ]
            ]
        },
        {
            "name": "storage"
        },
        {
            "name": "inhand-left",
            "directions": 4
        },
        {
            "name": "inhand-right",
            "directions": 4
        },
        {
            "name": "inhand-left-active",
            "directions": 4
        },
        {
            "name": "inhand-right-active",
            "directions": 4
        }
    ]
}
