{
  "version": 1,
  "license": "CC-BY-SA-3.0",
  "copyright": "Taken from tgstation at https://github.com/tgstation/tgstation/commit/e1142f20f5e4661cb6845cfcf2dd69f864d67432. stamp-syndicate is a modified version of stamp-warden. paper_stamp-syndicate by Veritius. paper_receipt by eoineoineoin. pen_centcom is a resprited version of pen_cap by PuroSlavKing (Github)",
  "size": {
    "x": 32,
    "y": 32
  },
  "states": [
    {
        "name": "stamp-iaa"
    },
    {
        "name": "paper_stamp-iaa"
    }
  ]
}
