{"version": 1, "size": {"x": 64, "y": 32}, "states": [{"name": "scanner_death", "directions": 1, "delays": [[0.3, 0.3, 0.3, 0.3]]}, {"name": "scanner_green", "directions": 1, "delays": [[0.3, 0.3, 0.3, 0.3, 0.3, 0.3]]}, {"name": "scanner_off", "directions": 1, "delays": [[1.0]]}, {"name": "scanner_open", "directions": 1, "delays": [[1.0]]}, {"name": "scanner_red", "directions": 1, "delays": [[0.3, 0.3, 0.3, 0.3, 0.3, 0.3]]}, {"name": "scanner_terminal_blue", "directions": 1, "delays": [[0.3, 0.3, 0.3, 0.3]]}, {"name": "scanner_terminal_dead", "directions": 1, "delays": [[0.2, 0.2, 0.2, 0.2]]}, {"name": "scanner_terminal_green", "directions": 1, "delays": [[0.3, 0.3, 0.3, 0.3]]}, {"name": "scanner_terminal_off", "directions": 1, "delays": [[1.0]]}, {"name": "scanner_terminal_red", "directions": 1, "delays": [[0.3, 0.3, 0.3, 0.3]]}, {"name": "scanner_yellow", "directions": 1, "delays": [[0.3, 0.3, 0.3, 0.3, 0.3, 0.3]]}]}