{
  "version": 1,
  "license": "CC-BY-SA-3.0",
  "copyright": "icons taked from Paradise Station; inhand, wield, and belt equip sprites by RiceMar1244",
  "size": {
    "x": 32,
    "y": 32
  },
    "states": [
        {
            "name": "icon",
            "delays": [
                [
                    0.1,
                    0.1,
                    0.1,
                    0.1,
                    0.1,
                    0.1,
                    0.1,
                    0.1
                ]
            ]
        },
        {
            "name": "animation-icon",
            "delays": [
                [
                    0.1,
                    0.1,
                    0.1,
                    0.1
                ]
            ]
        },
        {
            "name": "inhand-right",
            "directions": 4
        },
        {
            "name": "inhand-left",
            "directions": 4
        }
    ]
}
