{
  "version": 1,
  "license": "CC-BY-SA-3.0",
  "copyright": "Taken from cev-eris at https://github.com/discordia-space/CEV-Eris/raw/9c980cb9bc84d07b1c210c5447798af525185f80/icons/obj/food.dmi",
  "size": {
    "x": 32,
    "y": 32
  },
  "states": [
    {
      "name": "icon"
    },
    {
      "name": "icon-hot",
      "delays": [
        [
          0.5,
          0.5,
          0.5,
          0.5
        ]
      ]
    },
    {
      "name": "icon-open"
    },
    {
      "name": "trash"
    }
  ]
}
