{
  "version": 1,
  "license": "CC-BY-SA-3.0",
  "copyright": "Taken from tgstation at https://github.com/tgstation/tgstation/commit/cf45322c7ee16f9d7e43d5260daf24ceb77c1b25",
  "size": {
    "x": 32,
    "y": 32
  },
  "states": [
    {
      "name": "mmi_off"
    },
    {
      "name": "mmi_alive"
    },
    {
      "name": "mmi_dead"
    },
    {
      "name": "mmi_brain"
    },
    {
      "name": "mmi_brain_alien"
    },
    {
      "name": "posibrain"
    },
    {
      "name": "posibrain-occupied",
      "delays": [
        [
          0.1,
          0.1,
          0.1,
          0.1,
          0.1,
          0.1,
          0.1,
          0.1,
          0.1,
          0.1,
          0.1,
          0.1,
          0.1,
          0.1,
          0.1,
          0.1,
          0.1,
          0.1,
          0.1,
          0.1
        ]
      ]
    },
    {
      "name": "posibrain-searching",
      "delays": [
        [
          0.1,
          0.1,
          0.1,
          0.1,
          0.1,
          0.1,
          0.1,
          0.1,
          0.1,
          0.1,
          0.1,
          0.1,
          0.1,
          0.1,
          0.1,
          0.1
        ]
      ]
    }
  ]
}
